sprig/__init__.py
sprig/comb.py
sprig/dictutils.py
sprig/intervals.py
sprig/intervals_naive.py
sprig/iterutils.py
sprig/py.typed
sprig/streamutils.py
sprig/version.py
sprig-0.5.1.dist-info/LICENSE
sprig-0.5.1.dist-info/METADATA
sprig-0.5.1.dist-info/WHEEL
sprig-0.5.1.dist-info/top_level.txt
sprig-0.5.1.dist-info/RECORD
