Metadata-Version: 2.1
Name: sprig
Version: 0.5.1
Summary: A home to code that would otherwise be homeless
Home-page: https://github.com/apljungquist/sprig
Author: AP Ljungquist
Author-email: ap@ljungquist.eu
License: MIT
Platform: UNKNOWN
Classifier: Development Status :: 3 - Alpha
Classifier: Programming Language :: Python :: 3
Classifier: License :: OSI Approved :: MIT License
Classifier: Operating System :: OS Independent
License-File: LICENSE
Requires-Dist: more-itertools
Requires-Dist: typing-extensions
